{"metadata": {"dbt_schema_version": "https://schemas.getdbt.com/dbt/run-results/v6.json", "dbt_version": "1.11.8", "generated_at": "2026-04-12T01:48:01.728665Z", "invocation_id": "1c8d41c9-9ca8-4dd4-9eca-02f6b332064c", "invocation_started_at": "2026-04-12T01:48:00.946913Z", "env": {}}, "results": [{"status": "success", "timing": [{"name": "compile", "started_at": "2026-04-12T01:48:01.655270Z", "completed_at": "2026-04-12T01:48:01.661032Z"}, {"name": "execute", "started_at": "2026-04-12T01:48:01.664355Z", "completed_at": "2026-04-12T01:48:01.664376Z"}], "thread_id": "Thread-1 (worker)", "execution_time": 0.013369083404541016, "adapter_response": {}, "message": null, "failures": null, "unique_id": "seed.dwh_sm2.location_map", "compiled": null, "compiled_code": null, "relation_name": null, "batch_results": null}, {"status": "success", "timing": [{"name": "compile", "started_at": "2026-04-12T01:48:01.662031Z", "completed_at": "2026-04-12T01:48:01.663388Z"}, {"name": "execute", "started_at": "2026-04-12T01:48:01.668173Z", "completed_at": "2026-04-12T01:48:01.668184Z"}], "thread_id": "Thread-2 (worker)", "execution_time": 0.016129493713378906, "adapter_response": {}, "message": null, "failures": null, "unique_id": "seed.dwh_sm2.mapping", "compiled": null, "compiled_code": null, "relation_name": null, "batch_results": null}, {"status": "success", "timing": [{"name": "compile", "started_at": "2026-04-12T01:48:01.665151Z", "completed_at": "2026-04-12T01:48:01.667653Z"}, {"name": "execute", "started_at": "2026-04-12T01:48:01.670818Z", "completed_at": "2026-04-12T01:48:01.670829Z"}], "thread_id": "Thread-3 (worker)", "execution_time": 0.017271041870117188, "adapter_response": {}, "message": null, "failures": null, "unique_id": "seed.dwh_sm2.mapping_indoor", "compiled": null, "compiled_code": null, "relation_name": null, "batch_results": null}, {"status": "success", "timing": [{"name": "compile", "started_at": "2026-04-12T01:48:01.668914Z", "completed_at": "2026-04-12T01:48:01.670189Z"}, {"name": "execute", "started_at": "2026-04-12T01:48:01.671650Z", "completed_at": "2026-04-12T01:48:01.671659Z"}], "thread_id": "Thread-4 (worker)", "execution_time": 0.017151594161987305, "adapter_response": {}, "message": null, "failures": null, "unique_id": "seed.dwh_sm2.mapping_sources", "compiled": null, "compiled_code": null, "relation_name": null, "batch_results": null}, {"status": "success", "timing": [{"name": "compile", "started_at": "2026-04-12T01:48:01.681724Z", "completed_at": "2026-04-12T01:48:01.689554Z"}, {"name": "execute", "started_at": "2026-04-12T01:48:01.690550Z", "completed_at": "2026-04-12T01:48:01.690562Z"}], "thread_id": "Thread-7 (worker)", "execution_time": 0.01570606231689453, "adapter_response": {}, "message": null, "failures": null, "unique_id": "model.dwh_sm2.fact_indoor_humidity", "compiled": true, "compiled_code": "with source as (\n    select * from read_csv('./gdrive/all_sensors_merged.csv')\n),\n\nmapped as (\n    select\n        source.Datetime as \"time\", --noqa\n        mapping.location,\n        'humidity_indoor' as data_key,\n        source.\"Relative_Humidity(%)\" as data_value --noqa\n    from source\n    inner join \"dwh_sm2\".\"main\".\"mapping_indoor\" as mapping --noqa\n        on source.location = mapping.sensor\n    where source.datetime is not null\n),\n\nparams as (\n    select\n        date_trunc( --noqa\n            'month', now()) - interval (b.history - 1 --noqa\n            ) month as start_ts --noqa\n    from \"dwh_sm2\".\"main\".\"mapping_sources\" as b\n    where b.file_nm = 'fact_indoor_humidity.csv'\n),\n\nfinal as (\n    select\n        time,\n        location,\n        data_key,\n        data_value\n    from mapped\n    union distinct\n    select *\n    from read_csv('./gdrive/fact_indoor_humidity.csv')\n)\n\nselect *\nfrom final\nwhere time >= (select max(start_ts) from params) --noqa", "relation_name": "\"dwh_sm2\".\"main\".\"fact_indoor_humidity\"", "batch_results": null}, {"status": "success", "timing": [{"name": "compile", "started_at": "2026-04-12T01:48:01.685381Z", "completed_at": "2026-04-12T01:48:01.690088Z"}, {"name": "execute", "started_at": "2026-04-12T01:48:01.691798Z", "completed_at": "2026-04-12T01:48:01.691809Z"}], "thread_id": "Thread-8 (worker)", "execution_time": 0.015649795532226562, "adapter_response": {}, "message": null, "failures": null, "unique_id": "model.dwh_sm2.fact_indoor_temperature", "compiled": true, "compiled_code": "with source as (\n    select * from read_csv('./gdrive/all_sensors_merged.csv')\n),\n\nmapped as (\n    select\n        source.Datetime as \"time\", --noqa\n        mapping.location,\n        'temp_indoor' as data_key,\n        source.temperature_celsius as data_value\n    from source\n    inner join \"dwh_sm2\".\"main\".\"mapping_indoor\" as mapping --noqa\n        on source.location = mapping.sensor\n    where source.datetime is not null\n),\n\nparams as (\n    select\n        date_trunc( --noqa\n            'month', now()) - interval (b.history - 1 --noqa\n            ) month as start_ts --noqa\n    from \"dwh_sm2\".\"main\".\"mapping_sources\" as b\n    where b.file_nm = 'fact_indoor_temperature.csv'\n),\n\nfinal as (\n    select\n        time,\n        location,\n        data_key,\n        data_value\n    from mapped\n    union distinct\n    select *\n    from read_csv('./gdrive/fact_indoor_temperature.csv')\n)\n\nselect *\nfrom final\nwhere time >= (select max(start_ts) from params) --noqa", "relation_name": "\"dwh_sm2\".\"main\".\"fact_indoor_temperature\"", "batch_results": null}, {"status": "success", "timing": [{"name": "compile", "started_at": "2026-04-12T01:48:01.677264Z", "completed_at": "2026-04-12T01:48:01.691276Z"}, {"name": "execute", "started_at": "2026-04-12T01:48:01.692625Z", "completed_at": "2026-04-12T01:48:01.692633Z"}], "thread_id": "Thread-6 (worker)", "execution_time": 0.018824100494384766, "adapter_response": {}, "message": null, "failures": null, "unique_id": "model.dwh_sm2.fact", "compiled": true, "compiled_code": "with source as ( --noqa\n    select cast(columns(*) as varchar) from read_csv('./gdrive/merged.csv')\n),\n\nunpivoted as (\n    unpivot source --noqa\n    on columns(* exclude (date))\n    into\n    name data_key_original\n    value data_value\n),\n\nmapped as (\n    select\n        unpivoted.date as \"time\", --noqa\n        mapping.location,\n        mapping.data_key,\n        unpivoted.data_value\n    from unpivoted\n    inner join \"dwh_sm2\".\"main\".\"mapping\" as mapping --noqa\n        on unpivoted.data_key_original = mapping.data_key_original\n    where unpivoted.date is not null\n),\n\nparams as (\n    select\n        date_trunc( --noqa\n            'month', now()) - interval (b.history - 1 --noqa\n            ) month as start_ts --noqa\n    from \"dwh_sm2\".\"main\".\"mapping_sources\" as b\n    where b.file_nm = 'fact.csv'\n),\n\nfinal as (\n    select\n        cast(time as timestamp) as time, --noqa\n        location,\n        data_key,\n        data_value\n    from mapped\n    union distinct\n    select * from read_csv('./gdrive/fact.csv')\n)\n\nselect *\nfrom final\nwhere time >= (select max(start_ts) from params) --noqa", "relation_name": "\"dwh_sm2\".\"main\".\"fact\"", "batch_results": null}, {"status": "success", "timing": [{"name": "compile", "started_at": "2026-04-12T01:48:01.695005Z", "completed_at": "2026-04-12T01:48:01.710820Z"}, {"name": "execute", "started_at": "2026-04-12T01:48:01.719912Z", "completed_at": "2026-04-12T01:48:01.719924Z"}], "thread_id": "Thread-8 (worker)", "execution_time": 0.02592301368713379, "adapter_response": {}, "message": null, "failures": null, "unique_id": "test.dwh_sm2.not_null_fact_indoor_humidity_time.40897f2842", "compiled": true, "compiled_code": "\n    \n    \n\n\n\nselect time\nfrom \"dwh_sm2\".\"main\".\"fact_indoor_humidity\"\nwhere time is null\n\n\n", "relation_name": null, "batch_results": null}, {"status": "success", "timing": [{"name": "compile", "started_at": "2026-04-12T01:48:01.711309Z", "completed_at": "2026-04-12T01:48:01.721066Z"}, {"name": "execute", "started_at": "2026-04-12T01:48:01.722028Z", "completed_at": "2026-04-12T01:48:01.722036Z"}], "thread_id": "Thread-11 (worker)", "execution_time": 0.013492107391357422, "adapter_response": {}, "message": null, "failures": null, "unique_id": "test.dwh_sm2.not_null_fact_indoor_temperature_time.06175171ac", "compiled": true, "compiled_code": "\n    \n    \n\n\n\nselect time\nfrom \"dwh_sm2\".\"main\".\"fact_indoor_temperature\"\nwhere time is null\n\n\n", "relation_name": null, "batch_results": null}, {"status": "success", "timing": [{"name": "compile", "started_at": "2026-04-12T01:48:01.715561Z", "completed_at": "2026-04-12T01:48:01.721535Z"}, {"name": "execute", "started_at": "2026-04-12T01:48:01.722719Z", "completed_at": "2026-04-12T01:48:01.722727Z"}], "thread_id": "Thread-12 (worker)", "execution_time": 0.013502359390258789, "adapter_response": {}, "message": null, "failures": null, "unique_id": "test.dwh_sm2.not_null_fact_time.2257553dfe", "compiled": true, "compiled_code": "\n    \n    \n\n\n\nselect time\nfrom \"dwh_sm2\".\"main\".\"fact\"\nwhere time is null\n\n\n", "relation_name": null, "batch_results": null}], "elapsed_time": 0.14872455596923828, "args": {"compile": true, "validate_macro_args": false, "profiles_dir": "./", "show_resource_report": false, "introspect": true, "log_level": "info", "exclude": [], "require_nested_cumulative_type_params": false, "populate_cache": true, "invocation_command": "dbt docs generate", "static_parser": true, "require_resource_names_without_spaces": true, "send_anonymous_usage_stats": true, "use_colors": true, "macro_debugging": false, "source_freshness_run_project_hooks": true, "log_format_file": "debug", "require_all_warnings_handled_by_warn_error": false, "quiet": false, "require_generic_test_arguments_property": true, "state_modified_compare_vars": false, "vars": {}, "favor_state": false, "version_check": true, "require_unique_project_resource_names": false, "log_file_max_bytes": 10485760, "use_colors_file": true, "use_fast_test_edges": false, "skip_nodes_if_on_run_start_fails": false, "cache_selected_only": false, "log_format": "default", "warn_error_options": {"error": [], "warn": [], "silence": []}, "print": true, "printer_width": 80, "project_dir": "/home/runner/work/dwh-sm2/dwh-sm2", "require_batched_execution_for_custom_microbatch_strategy": false, "require_explicit_package_overrides_for_builtin_materializations": true, "select": [], "sqlparse": {"MAX_GROUPING_DEPTH": null, "MAX_GROUPING_TOKENS": null}, "partial_parse_file_diff": true, "state_modified_compare_more_unrendered_values": false, "which": "generate", "indirect_selection": "eager", "show_all_deprecations": false, "require_ref_searches_node_package_before_root": false, "defer": false, "empty_catalog": false, "require_yaml_configuration_for_mf_time_spines": false, "partial_parse": true, "log_level_file": "debug", "static": false, "upload_to_artifacts_ingest_api": false, "strict_mode": false, "log_path": "/home/runner/work/dwh-sm2/dwh-sm2/logs", "write_json": true}}