{"metadata": {"dbt_schema_version": "https://schemas.getdbt.com/dbt/run-results/v6.json", "dbt_version": "1.10.8", "generated_at": "2025-08-14T01:01:41.222996Z", "invocation_id": "50adb591-cdb7-4004-9090-6be84fe8414e", "invocation_started_at": "2025-08-14T01:01:40.448630Z", "env": {}}, "results": [{"status": "success", "timing": [{"name": "compile", "started_at": "2025-08-14T01:01:41.151526Z", "completed_at": "2025-08-14T01:01:41.157963Z"}, {"name": "execute", "started_at": "2025-08-14T01:01:41.160865Z", "completed_at": "2025-08-14T01:01:41.160886Z"}], "thread_id": "Thread-1 (worker)", "execution_time": 0.012714624404907227, "adapter_response": {}, "message": null, "failures": null, "unique_id": "seed.dwh_sm2.mapping", "compiled": null, "compiled_code": null, "relation_name": null, "batch_results": null}, {"status": "success", "timing": [{"name": "compile", "started_at": "2025-08-14T01:01:41.158974Z", "completed_at": "2025-08-14T01:01:41.160374Z"}, {"name": "execute", "started_at": "2025-08-14T01:01:41.163486Z", "completed_at": "2025-08-14T01:01:41.163497Z"}], "thread_id": "Thread-2 (worker)", "execution_time": 0.01422882080078125, "adapter_response": {}, "message": null, "failures": null, "unique_id": "seed.dwh_sm2.mapping_indoor", "compiled": null, "compiled_code": null, "relation_name": null, "batch_results": null}, {"status": "success", "timing": [{"name": "compile", "started_at": "2025-08-14T01:01:41.161686Z", "completed_at": "2025-08-14T01:01:41.162999Z"}, {"name": "execute", "started_at": "2025-08-14T01:01:41.164413Z", "completed_at": "2025-08-14T01:01:41.164421Z"}], "thread_id": "Thread-3 (worker)", "execution_time": 0.014044046401977539, "adapter_response": {}, "message": null, "failures": null, "unique_id": "seed.dwh_sm2.mapping_sources", "compiled": null, "compiled_code": null, "relation_name": null, "batch_results": null}, {"status": "success", "timing": [{"name": "compile", "started_at": "2025-08-14T01:01:41.178167Z", "completed_at": "2025-08-14T01:01:41.182283Z"}, {"name": "execute", "started_at": "2025-08-14T01:01:41.182775Z", "completed_at": "2025-08-14T01:01:41.182788Z"}], "thread_id": "Thread-7 (worker)", "execution_time": 0.009987115859985352, "adapter_response": {}, "message": null, "failures": null, "unique_id": "model.dwh_sm2.fact_indoor_temperature", "compiled": true, "compiled_code": "with source as (\n    select * from read_csv('./gdrive/all_sensors_merged.csv')\n),\n\nmapped as (\n    select\n        source.Datetime as \"time\", --noqa\n        mapping.location,\n        'temp_indoor' as data_key,\n        source.temperature_celsius as data_value\n    from source\n    inner join \"dwh_sm2\".\"main\".\"mapping_indoor\" as mapping --noqa\n        on source.location = mapping.sensor\n    where source.datetime is not null\n),\n\nparams as (\n    select\n        date_trunc( --noqa\n            'month', now()) - interval (b.history - 1 --noqa\n            ) month as start_ts --noqa\n    from \"dwh_sm2\".\"main\".\"mapping_sources\" as b\n    where b.file_nm = 'fact_indoor_temperature.csv'\n),\n\nfinal as (\n    select\n        time,\n        location,\n        data_key,\n        data_value\n    from mapped\n    union distinct\n    select *\n    from read_csv('./gdrive/fact_indoor_temperature.csv')\n)\n\nselect *\nfrom final\nwhere time >= (select max(start_ts) from params) --noqa", "relation_name": "\"dwh_sm2\".\"main\".\"fact_indoor_temperature\"", "batch_results": null}, {"status": "success", "timing": [{"name": "compile", "started_at": "2025-08-14T01:01:41.167730Z", "completed_at": "2025-08-14T01:01:41.183663Z"}, {"name": "execute", "started_at": "2025-08-14T01:01:41.184749Z", "completed_at": "2025-08-14T01:01:41.184758Z"}], "thread_id": "Thread-5 (worker)", "execution_time": 0.01859426498413086, "adapter_response": {}, "message": null, "failures": null, "unique_id": "model.dwh_sm2.fact", "compiled": true, "compiled_code": "with source as ( --noqa\n    select cast(columns(*) as varchar) from read_csv('./gdrive/merged.csv')\n),\n\nunpivoted as (\n    unpivot source --noqa\n    on columns(* exclude (date))\n    into\n    name data_key_original\n    value data_value\n),\n\nmapped as (\n    select\n        unpivoted.date as \"time\", --noqa\n        mapping.location,\n        mapping.data_key,\n        unpivoted.data_value\n    from unpivoted\n    inner join \"dwh_sm2\".\"main\".\"mapping\" as mapping --noqa\n        on unpivoted.data_key_original = mapping.data_key_original\n    where unpivoted.date is not null\n),\n\nparams as (\n    select\n        date_trunc( --noqa\n            'month', now()) - interval (b.history - 1 --noqa\n            ) month as start_ts --noqa\n    from \"dwh_sm2\".\"main\".\"mapping_sources\" as b\n    where b.file_nm = 'fact.csv'\n),\n\nfinal as (\n    select\n        cast(time as timestamp) as time, --noqa\n        location,\n        data_key,\n        data_value\n    from mapped\n    union distinct\n    select * from read_csv('./gdrive/fact.csv')\n)\n\nselect *\nfrom final\nwhere time >= (select max(start_ts) from params) --noqa", "relation_name": "\"dwh_sm2\".\"main\".\"fact\"", "batch_results": null}, {"status": "success", "timing": [{"name": "compile", "started_at": "2025-08-14T01:01:41.174537Z", "completed_at": "2025-08-14T01:01:41.184196Z"}, {"name": "execute", "started_at": "2025-08-14T01:01:41.186038Z", "completed_at": "2025-08-14T01:01:41.186047Z"}], "thread_id": "Thread-6 (worker)", "execution_time": 0.013889312744140625, "adapter_response": {}, "message": null, "failures": null, "unique_id": "model.dwh_sm2.fact_indoor_humidity", "compiled": true, "compiled_code": "with source as (\n    select * from read_csv('./gdrive/all_sensors_merged.csv')\n),\n\nmapped as (\n    select\n        source.Datetime as \"time\", --noqa\n        mapping.location,\n        'humidity_indoor' as data_key,\n        source.\"Relative_Humidity(%)\" as data_value --noqa\n    from source\n    inner join \"dwh_sm2\".\"main\".\"mapping_indoor\" as mapping --noqa\n        on source.location = mapping.sensor\n    where source.datetime is not null\n),\n\nparams as (\n    select\n        date_trunc( --noqa\n            'month', now()) - interval (b.history - 1 --noqa\n            ) month as start_ts --noqa\n    from \"dwh_sm2\".\"main\".\"mapping_sources\" as b\n    where b.file_nm = 'fact_indoor_humidity.csv'\n),\n\nfinal as (\n    select\n        time,\n        location,\n        data_key,\n        data_value\n    from mapped\n    union distinct\n    select *\n    from read_csv('./gdrive/fact_indoor_humidity.csv')\n)\n\nselect *\nfrom final\nwhere time >= (select max(start_ts) from params) --noqa", "relation_name": "\"dwh_sm2\".\"main\".\"fact_indoor_humidity\"", "batch_results": null}, {"status": "success", "timing": [{"name": "compile", "started_at": "2025-08-14T01:01:41.209227Z", "completed_at": "2025-08-14T01:01:41.213646Z"}, {"name": "execute", "started_at": "2025-08-14T01:01:41.214171Z", "completed_at": "2025-08-14T01:01:41.214185Z"}], "thread_id": "Thread-12 (worker)", "execution_time": 0.014049530029296875, "adapter_response": {}, "message": null, "failures": null, "unique_id": "test.dwh_sm2.not_null_fact_indoor_humidity_time.40897f2842", "compiled": true, "compiled_code": "\n    \n    \n\n\n\nselect time\nfrom \"dwh_sm2\".\"main\".\"fact_indoor_humidity\"\nwhere time is null\n\n\n", "relation_name": null, "batch_results": null}, {"status": "success", "timing": [{"name": "compile", "started_at": "2025-08-14T01:01:41.189727Z", "completed_at": "2025-08-14T01:01:41.215091Z"}, {"name": "execute", "started_at": "2025-08-14T01:01:41.216076Z", "completed_at": "2025-08-14T01:01:41.216085Z"}], "thread_id": "Thread-9 (worker)", "execution_time": 0.029268503189086914, "adapter_response": {}, "message": null, "failures": null, "unique_id": "test.dwh_sm2.not_null_fact_indoor_temperature_time.06175171ac", "compiled": true, "compiled_code": "\n    \n    \n\n\n\nselect time\nfrom \"dwh_sm2\".\"main\".\"fact_indoor_temperature\"\nwhere time is null\n\n\n", "relation_name": null, "batch_results": null}, {"status": "success", "timing": [{"name": "compile", "started_at": "2025-08-14T01:01:41.204921Z", "completed_at": "2025-08-14T01:01:41.215579Z"}, {"name": "execute", "started_at": "2025-08-14T01:01:41.216818Z", "completed_at": "2025-08-14T01:01:41.216826Z"}], "thread_id": "Thread-6 (worker)", "execution_time": 0.027680635452270508, "adapter_response": {}, "message": null, "failures": null, "unique_id": "test.dwh_sm2.not_null_fact_time.2257553dfe", "compiled": true, "compiled_code": "\n    \n    \n\n\n\nselect time\nfrom \"dwh_sm2\".\"main\".\"fact\"\nwhere time is null\n\n\n", "relation_name": null, "batch_results": null}], "elapsed_time": 0.15559077262878418, "args": {"cache_selected_only": false, "source_freshness_run_project_hooks": true, "use_colors": true, "use_colors_file": true, "require_resource_names_without_spaces": true, "indirect_selection": "eager", "printer_width": 80, "upload_to_artifacts_ingest_api": false, "log_format_file": "debug", "partial_parse_file_diff": true, "send_anonymous_usage_stats": true, "compile": true, "write_json": true, "vars": {}, "log_path": "/home/runner/work/dwh-sm2/dwh-sm2/logs", "skip_nodes_if_on_run_start_fails": false, "use_fast_test_edges": false, "select": [], "state_modified_compare_more_unrendered_values": false, "populate_cache": true, "profiles_dir": "./", "require_nested_cumulative_type_params": false, "require_all_warnings_handled_by_warn_error": false, "macro_debugging": false, "show_all_deprecations": false, "validate_macro_args": false, "project_dir": "/home/runner/work/dwh-sm2/dwh-sm2", "version_check": true, "defer": false, "static_parser": true, "static": false, "quiet": false, "require_generic_test_arguments_property": true, "partial_parse": true, "log_level_file": "debug", "empty_catalog": false, "strict_mode": false, "exclude": [], "invocation_command": "dbt docs generate", "introspect": true, "require_batched_execution_for_custom_microbatch_strategy": false, "print": true, "show_resource_report": false, "state_modified_compare_vars": false, "log_level": "info", "favor_state": false, "warn_error_options": {"error": [], "warn": [], "silence": []}, "require_explicit_package_overrides_for_builtin_materializations": true, "log_file_max_bytes": 10485760, "which": "generate", "require_yaml_configuration_for_mf_time_spines": false, "log_format": "default"}}