{"metadata": {"dbt_schema_version": "https://schemas.getdbt.com/dbt/run-results/v6.json", "dbt_version": "1.10.11", "generated_at": "2025-09-16T00:54:34.705644Z", "invocation_id": "f3d5484e-e8b6-49e1-a1cf-0d4cb0e24071", "invocation_started_at": "2025-09-16T00:54:33.920269Z", "env": {}}, "results": [{"status": "success", "timing": [{"name": "compile", "started_at": "2025-09-16T00:54:34.628595Z", "completed_at": "2025-09-16T00:54:34.635230Z"}, {"name": "execute", "started_at": "2025-09-16T00:54:34.638737Z", "completed_at": "2025-09-16T00:54:34.638754Z"}], "thread_id": "Thread-1 (worker)", "execution_time": 0.014535903930664062, "adapter_response": {}, "message": null, "failures": null, "unique_id": "seed.dwh_sm2.location_map", "compiled": null, "compiled_code": null, "relation_name": null, "batch_results": null}, {"status": "success", "timing": [{"name": "compile", "started_at": "2025-09-16T00:54:34.636345Z", "completed_at": "2025-09-16T00:54:34.637658Z"}, {"name": "execute", "started_at": "2025-09-16T00:54:34.641460Z", "completed_at": "2025-09-16T00:54:34.641471Z"}], "thread_id": "Thread-2 (worker)", "execution_time": 0.016173362731933594, "adapter_response": {}, "message": null, "failures": null, "unique_id": "seed.dwh_sm2.mapping", "compiled": null, "compiled_code": null, "relation_name": null, "batch_results": null}, {"status": "success", "timing": [{"name": "compile", "started_at": "2025-09-16T00:54:34.639578Z", "completed_at": "2025-09-16T00:54:34.640958Z"}, {"name": "execute", "started_at": "2025-09-16T00:54:34.644150Z", "completed_at": "2025-09-16T00:54:34.644159Z"}], "thread_id": "Thread-3 (worker)", "execution_time": 0.01731419563293457, "adapter_response": {}, "message": null, "failures": null, "unique_id": "seed.dwh_sm2.mapping_indoor", "compiled": null, "compiled_code": null, "relation_name": null, "batch_results": null}, {"status": "success", "timing": [{"name": "compile", "started_at": "2025-09-16T00:54:34.642260Z", "completed_at": "2025-09-16T00:54:34.643520Z"}, {"name": "execute", "started_at": "2025-09-16T00:54:34.645024Z", "completed_at": "2025-09-16T00:54:34.645032Z"}], "thread_id": "Thread-4 (worker)", "execution_time": 0.017096996307373047, "adapter_response": {}, "message": null, "failures": null, "unique_id": "seed.dwh_sm2.mapping_sources", "compiled": null, "compiled_code": null, "relation_name": null, "batch_results": null}, {"status": "success", "timing": [{"name": "compile", "started_at": "2025-09-16T00:54:34.647861Z", "completed_at": "2025-09-16T00:54:34.663343Z"}, {"name": "execute", "started_at": "2025-09-16T00:54:34.663947Z", "completed_at": "2025-09-16T00:54:34.663962Z"}], "thread_id": "Thread-6 (worker)", "execution_time": 0.017299652099609375, "adapter_response": {}, "message": null, "failures": null, "unique_id": "model.dwh_sm2.fact", "compiled": true, "compiled_code": "with source as ( --noqa\n    select cast(columns(*) as varchar) from read_csv('./gdrive/merged.csv')\n),\n\nunpivoted as (\n    unpivot source --noqa\n    on columns(* exclude (date))\n    into\n    name data_key_original\n    value data_value\n),\n\nmapped as (\n    select\n        unpivoted.date as \"time\", --noqa\n        mapping.location,\n        mapping.data_key,\n        unpivoted.data_value\n    from unpivoted\n    inner join \"dwh_sm2\".\"main\".\"mapping\" as mapping --noqa\n        on unpivoted.data_key_original = mapping.data_key_original\n    where unpivoted.date is not null\n),\n\nparams as (\n    select\n        date_trunc( --noqa\n            'month', now()) - interval (b.history - 1 --noqa\n            ) month as start_ts --noqa\n    from \"dwh_sm2\".\"main\".\"mapping_sources\" as b\n    where b.file_nm = 'fact.csv'\n),\n\nfinal as (\n    select\n        cast(time as timestamp) as time, --noqa\n        location,\n        data_key,\n        data_value\n    from mapped\n    union distinct\n    select * from read_csv('./gdrive/fact.csv')\n)\n\nselect *\nfrom final\nwhere time >= (select max(start_ts) from params) --noqa", "relation_name": "\"dwh_sm2\".\"main\".\"fact\"", "batch_results": null}, {"status": "success", "timing": [{"name": "compile", "started_at": "2025-09-16T00:54:34.655521Z", "completed_at": "2025-09-16T00:54:34.664965Z"}, {"name": "execute", "started_at": "2025-09-16T00:54:34.665496Z", "completed_at": "2025-09-16T00:54:34.665505Z"}], "thread_id": "Thread-7 (worker)", "execution_time": 0.012307882308959961, "adapter_response": {}, "message": null, "failures": null, "unique_id": "model.dwh_sm2.fact_indoor_humidity", "compiled": true, "compiled_code": "with source as (\n    select * from read_csv('./gdrive/all_sensors_merged.csv')\n),\n\nmapped as (\n    select\n        source.Datetime as \"time\", --noqa\n        mapping.location,\n        'humidity_indoor' as data_key,\n        source.\"Relative_Humidity(%)\" as data_value --noqa\n    from source\n    inner join \"dwh_sm2\".\"main\".\"mapping_indoor\" as mapping --noqa\n        on source.location = mapping.sensor\n    where source.datetime is not null\n),\n\nparams as (\n    select\n        date_trunc( --noqa\n            'month', now()) - interval (b.history - 1 --noqa\n            ) month as start_ts --noqa\n    from \"dwh_sm2\".\"main\".\"mapping_sources\" as b\n    where b.file_nm = 'fact_indoor_humidity.csv'\n),\n\nfinal as (\n    select\n        time,\n        location,\n        data_key,\n        data_value\n    from mapped\n    union distinct\n    select *\n    from read_csv('./gdrive/fact_indoor_humidity.csv')\n)\n\nselect *\nfrom final\nwhere time >= (select max(start_ts) from params) --noqa", "relation_name": "\"dwh_sm2\".\"main\".\"fact_indoor_humidity\"", "batch_results": null}, {"status": "success", "timing": [{"name": "compile", "started_at": "2025-09-16T00:54:34.659213Z", "completed_at": "2025-09-16T00:54:34.677691Z"}, {"name": "execute", "started_at": "2025-09-16T00:54:34.682094Z", "completed_at": "2025-09-16T00:54:34.682105Z"}], "thread_id": "Thread-8 (worker)", "execution_time": 0.028337955474853516, "adapter_response": {}, "message": null, "failures": null, "unique_id": "model.dwh_sm2.fact_indoor_temperature", "compiled": true, "compiled_code": "with source as (\n    select * from read_csv('./gdrive/all_sensors_merged.csv')\n),\n\nmapped as (\n    select\n        source.Datetime as \"time\", --noqa\n        mapping.location,\n        'temp_indoor' as data_key,\n        source.temperature_celsius as data_value\n    from source\n    inner join \"dwh_sm2\".\"main\".\"mapping_indoor\" as mapping --noqa\n        on source.location = mapping.sensor\n    where source.datetime is not null\n),\n\nparams as (\n    select\n        date_trunc( --noqa\n            'month', now()) - interval (b.history - 1 --noqa\n            ) month as start_ts --noqa\n    from \"dwh_sm2\".\"main\".\"mapping_sources\" as b\n    where b.file_nm = 'fact_indoor_temperature.csv'\n),\n\nfinal as (\n    select\n        time,\n        location,\n        data_key,\n        data_value\n    from mapped\n    union distinct\n    select *\n    from read_csv('./gdrive/fact_indoor_temperature.csv')\n)\n\nselect *\nfrom final\nwhere time >= (select max(start_ts) from params) --noqa", "relation_name": "\"dwh_sm2\".\"main\".\"fact_indoor_temperature\"", "batch_results": null}, {"status": "success", "timing": [{"name": "compile", "started_at": "2025-09-16T00:54:34.667797Z", "completed_at": "2025-09-16T00:54:34.684889Z"}, {"name": "execute", "started_at": "2025-09-16T00:54:34.691105Z", "completed_at": "2025-09-16T00:54:34.691115Z"}], "thread_id": "Thread-7 (worker)", "execution_time": 0.02443385124206543, "adapter_response": {}, "message": null, "failures": null, "unique_id": "test.dwh_sm2.not_null_fact_time.2257553dfe", "compiled": true, "compiled_code": "\n    \n    \n\n\n\nselect time\nfrom \"dwh_sm2\".\"main\".\"fact\"\nwhere time is null\n\n\n", "relation_name": null, "batch_results": null}, {"status": "success", "timing": [{"name": "compile", "started_at": "2025-09-16T00:54:34.685971Z", "completed_at": "2025-09-16T00:54:34.697354Z"}, {"name": "execute", "started_at": "2025-09-16T00:54:34.698366Z", "completed_at": "2025-09-16T00:54:34.698378Z"}], "thread_id": "Thread-10 (worker)", "execution_time": 0.015493631362915039, "adapter_response": {}, "message": null, "failures": null, "unique_id": "test.dwh_sm2.not_null_fact_indoor_humidity_time.40897f2842", "compiled": true, "compiled_code": "\n    \n    \n\n\n\nselect time\nfrom \"dwh_sm2\".\"main\".\"fact_indoor_humidity\"\nwhere time is null\n\n\n", "relation_name": null, "batch_results": null}, {"status": "success", "timing": [{"name": "compile", "started_at": "2025-09-16T00:54:34.693096Z", "completed_at": "2025-09-16T00:54:34.697832Z"}, {"name": "execute", "started_at": "2025-09-16T00:54:34.699150Z", "completed_at": "2025-09-16T00:54:34.699159Z"}], "thread_id": "Thread-12 (worker)", "execution_time": 0.0138397216796875, "adapter_response": {}, "message": null, "failures": null, "unique_id": "test.dwh_sm2.not_null_fact_indoor_temperature_time.06175171ac", "compiled": true, "compiled_code": "\n    \n    \n\n\n\nselect time\nfrom \"dwh_sm2\".\"main\".\"fact_indoor_temperature\"\nwhere time is null\n\n\n", "relation_name": null, "batch_results": null}], "elapsed_time": 0.16094183921813965, "args": {"strict_mode": false, "macro_debugging": false, "vars": {}, "static_parser": true, "compile": true, "log_format": "default", "which": "generate", "warn_error_options": {"error": [], "warn": [], "silence": []}, "invocation_command": "dbt docs generate", "use_colors": true, "print": true, "require_batched_execution_for_custom_microbatch_strategy": false, "log_level": "info", "profiles_dir": "./", "printer_width": 80, "require_resource_names_without_spaces": true, "log_file_max_bytes": 10485760, "send_anonymous_usage_stats": true, "use_fast_test_edges": false, "show_all_deprecations": false, "write_json": true, "introspect": true, "log_format_file": "debug", "project_dir": "/home/runner/work/dwh-sm2/dwh-sm2", "show_resource_report": false, "state_modified_compare_more_unrendered_values": false, "static": false, "require_all_warnings_handled_by_warn_error": false, "state_modified_compare_vars": false, "favor_state": false, "empty_catalog": false, "skip_nodes_if_on_run_start_fails": false, "require_explicit_package_overrides_for_builtin_materializations": true, "log_level_file": "debug", "require_yaml_configuration_for_mf_time_spines": false, "version_check": true, "partial_parse_file_diff": true, "exclude": [], "cache_selected_only": false, "require_nested_cumulative_type_params": false, "validate_macro_args": false, "use_colors_file": true, "select": [], "defer": false, "quiet": false, "source_freshness_run_project_hooks": true, "partial_parse": true, "upload_to_artifacts_ingest_api": false, "populate_cache": true, "require_generic_test_arguments_property": true, "indirect_selection": "eager", "log_path": "/home/runner/work/dwh-sm2/dwh-sm2/logs"}}