{"metadata": {"dbt_schema_version": "https://schemas.getdbt.com/dbt/run-results/v6.json", "dbt_version": "1.11.6", "generated_at": "2026-02-28T01:09:46.964373Z", "invocation_id": "992d8905-68f5-4979-b9d5-eb4a49a378f3", "invocation_started_at": "2026-02-28T01:09:46.177264Z", "env": {}}, "results": [{"status": "success", "timing": [{"name": "compile", "started_at": "2026-02-28T01:09:46.890062Z", "completed_at": "2026-02-28T01:09:46.896401Z"}, {"name": "execute", "started_at": "2026-02-28T01:09:46.901127Z", "completed_at": "2026-02-28T01:09:46.901144Z"}], "thread_id": "Thread-1 (worker)", "execution_time": 0.01529073715209961, "adapter_response": {}, "message": null, "failures": null, "unique_id": "seed.dwh_sm2.location_map", "compiled": null, "compiled_code": null, "relation_name": null, "batch_results": null}, {"status": "success", "timing": [{"name": "compile", "started_at": "2026-02-28T01:09:46.896988Z", "completed_at": "2026-02-28T01:09:46.898360Z"}, {"name": "execute", "started_at": "2026-02-28T01:09:46.901922Z", "completed_at": "2026-02-28T01:09:46.901932Z"}], "thread_id": "Thread-2 (worker)", "execution_time": 0.015042543411254883, "adapter_response": {}, "message": null, "failures": null, "unique_id": "seed.dwh_sm2.mapping", "compiled": null, "compiled_code": null, "relation_name": null, "batch_results": null}, {"status": "success", "timing": [{"name": "compile", "started_at": "2026-02-28T01:09:46.899304Z", "completed_at": "2026-02-28T01:09:46.900650Z"}, {"name": "execute", "started_at": "2026-02-28T01:09:46.904595Z", "completed_at": "2026-02-28T01:09:46.904603Z"}], "thread_id": "Thread-3 (worker)", "execution_time": 0.01618790626525879, "adapter_response": {}, "message": null, "failures": null, "unique_id": "seed.dwh_sm2.mapping_indoor", "compiled": null, "compiled_code": null, "relation_name": null, "batch_results": null}, {"status": "success", "timing": [{"name": "compile", "started_at": "2026-02-28T01:09:46.902657Z", "completed_at": "2026-02-28T01:09:46.903948Z"}, {"name": "execute", "started_at": "2026-02-28T01:09:46.905539Z", "completed_at": "2026-02-28T01:09:46.905548Z"}], "thread_id": "Thread-4 (worker)", "execution_time": 0.01617264747619629, "adapter_response": {}, "message": null, "failures": null, "unique_id": "seed.dwh_sm2.mapping_sources", "compiled": null, "compiled_code": null, "relation_name": null, "batch_results": null}, {"status": "success", "timing": [{"name": "compile", "started_at": "2026-02-28T01:09:46.915154Z", "completed_at": "2026-02-28T01:09:46.922769Z"}, {"name": "execute", "started_at": "2026-02-28T01:09:46.923305Z", "completed_at": "2026-02-28T01:09:46.923316Z"}], "thread_id": "Thread-7 (worker)", "execution_time": 0.014661550521850586, "adapter_response": {}, "message": null, "failures": null, "unique_id": "model.dwh_sm2.fact_indoor_humidity", "compiled": true, "compiled_code": "with source as (\n    select * from read_csv('./gdrive/all_sensors_merged.csv')\n),\n\nmapped as (\n    select\n        source.Datetime as \"time\", --noqa\n        mapping.location,\n        'humidity_indoor' as data_key,\n        source.\"Relative_Humidity(%)\" as data_value --noqa\n    from source\n    inner join \"dwh_sm2\".\"main\".\"mapping_indoor\" as mapping --noqa\n        on source.location = mapping.sensor\n    where source.datetime is not null\n),\n\nparams as (\n    select\n        date_trunc( --noqa\n            'month', now()) - interval (b.history - 1 --noqa\n            ) month as start_ts --noqa\n    from \"dwh_sm2\".\"main\".\"mapping_sources\" as b\n    where b.file_nm = 'fact_indoor_humidity.csv'\n),\n\nfinal as (\n    select\n        time,\n        location,\n        data_key,\n        data_value\n    from mapped\n    union distinct\n    select *\n    from read_csv('./gdrive/fact_indoor_humidity.csv')\n)\n\nselect *\nfrom final\nwhere time >= (select max(start_ts) from params) --noqa", "relation_name": "\"dwh_sm2\".\"main\".\"fact_indoor_humidity\"", "batch_results": null}, {"status": "success", "timing": [{"name": "compile", "started_at": "2026-02-28T01:09:46.918820Z", "completed_at": "2026-02-28T01:09:46.924268Z"}, {"name": "execute", "started_at": "2026-02-28T01:09:46.924761Z", "completed_at": "2026-02-28T01:09:46.924770Z"}], "thread_id": "Thread-8 (worker)", "execution_time": 0.01508784294128418, "adapter_response": {}, "message": null, "failures": null, "unique_id": "model.dwh_sm2.fact_indoor_temperature", "compiled": true, "compiled_code": "with source as (\n    select * from read_csv('./gdrive/all_sensors_merged.csv')\n),\n\nmapped as (\n    select\n        source.Datetime as \"time\", --noqa\n        mapping.location,\n        'temp_indoor' as data_key,\n        source.temperature_celsius as data_value\n    from source\n    inner join \"dwh_sm2\".\"main\".\"mapping_indoor\" as mapping --noqa\n        on source.location = mapping.sensor\n    where source.datetime is not null\n),\n\nparams as (\n    select\n        date_trunc( --noqa\n            'month', now()) - interval (b.history - 1 --noqa\n            ) month as start_ts --noqa\n    from \"dwh_sm2\".\"main\".\"mapping_sources\" as b\n    where b.file_nm = 'fact_indoor_temperature.csv'\n),\n\nfinal as (\n    select\n        time,\n        location,\n        data_key,\n        data_value\n    from mapped\n    union distinct\n    select *\n    from read_csv('./gdrive/fact_indoor_temperature.csv')\n)\n\nselect *\nfrom final\nwhere time >= (select max(start_ts) from params) --noqa", "relation_name": "\"dwh_sm2\".\"main\".\"fact_indoor_temperature\"", "batch_results": null}, {"status": "success", "timing": [{"name": "compile", "started_at": "2026-02-28T01:09:46.910763Z", "completed_at": "2026-02-28T01:09:46.926732Z"}, {"name": "execute", "started_at": "2026-02-28T01:09:46.928199Z", "completed_at": "2026-02-28T01:09:46.928208Z"}], "thread_id": "Thread-6 (worker)", "execution_time": 0.020537853240966797, "adapter_response": {}, "message": null, "failures": null, "unique_id": "model.dwh_sm2.fact", "compiled": true, "compiled_code": "with source as ( --noqa\n    select cast(columns(*) as varchar) from read_csv('./gdrive/merged.csv')\n),\n\nunpivoted as (\n    unpivot source --noqa\n    on columns(* exclude (date))\n    into\n    name data_key_original\n    value data_value\n),\n\nmapped as (\n    select\n        unpivoted.date as \"time\", --noqa\n        mapping.location,\n        mapping.data_key,\n        unpivoted.data_value\n    from unpivoted\n    inner join \"dwh_sm2\".\"main\".\"mapping\" as mapping --noqa\n        on unpivoted.data_key_original = mapping.data_key_original\n    where unpivoted.date is not null\n),\n\nparams as (\n    select\n        date_trunc( --noqa\n            'month', now()) - interval (b.history - 1 --noqa\n            ) month as start_ts --noqa\n    from \"dwh_sm2\".\"main\".\"mapping_sources\" as b\n    where b.file_nm = 'fact.csv'\n),\n\nfinal as (\n    select\n        cast(time as timestamp) as time, --noqa\n        location,\n        data_key,\n        data_value\n    from mapped\n    union distinct\n    select * from read_csv('./gdrive/fact.csv')\n)\n\nselect *\nfrom final\nwhere time >= (select max(start_ts) from params) --noqa", "relation_name": "\"dwh_sm2\".\"main\".\"fact\"", "batch_results": null}, {"status": "success", "timing": [{"name": "compile", "started_at": "2026-02-28T01:09:46.928950Z", "completed_at": "2026-02-28T01:09:46.950196Z"}, {"name": "execute", "started_at": "2026-02-28T01:09:46.951598Z", "completed_at": "2026-02-28T01:09:46.951610Z"}], "thread_id": "Thread-10 (worker)", "execution_time": 0.025584936141967773, "adapter_response": {}, "message": null, "failures": null, "unique_id": "test.dwh_sm2.not_null_fact_indoor_humidity_time.40897f2842", "compiled": true, "compiled_code": "\n    \n    \n\n\n\nselect time\nfrom \"dwh_sm2\".\"main\".\"fact_indoor_humidity\"\nwhere time is null\n\n\n", "relation_name": null, "batch_results": null}, {"status": "success", "timing": [{"name": "compile", "started_at": "2026-02-28T01:09:46.944621Z", "completed_at": "2026-02-28T01:09:46.950697Z"}, {"name": "execute", "started_at": "2026-02-28T01:09:46.952314Z", "completed_at": "2026-02-28T01:09:46.952323Z"}], "thread_id": "Thread-12 (worker)", "execution_time": 0.018346071243286133, "adapter_response": {}, "message": null, "failures": null, "unique_id": "test.dwh_sm2.not_null_fact_indoor_temperature_time.06175171ac", "compiled": true, "compiled_code": "\n    \n    \n\n\n\nselect time\nfrom \"dwh_sm2\".\"main\".\"fact_indoor_temperature\"\nwhere time is null\n\n\n", "relation_name": null, "batch_results": null}, {"status": "success", "timing": [{"name": "compile", "started_at": "2026-02-28T01:09:46.953016Z", "completed_at": "2026-02-28T01:09:46.957619Z"}, {"name": "execute", "started_at": "2026-02-28T01:09:46.958070Z", "completed_at": "2026-02-28T01:09:46.958077Z"}], "thread_id": "Thread-14 (worker)", "execution_time": 0.008826255798339844, "adapter_response": {}, "message": null, "failures": null, "unique_id": "test.dwh_sm2.not_null_fact_time.2257553dfe", "compiled": true, "compiled_code": "\n    \n    \n\n\n\nselect time\nfrom \"dwh_sm2\".\"main\".\"fact\"\nwhere time is null\n\n\n", "relation_name": null, "batch_results": null}], "elapsed_time": 0.1594374179840088, "args": {"use_colors_file": true, "log_level": "info", "require_all_warnings_handled_by_warn_error": false, "show_all_deprecations": false, "indirect_selection": "eager", "profiles_dir": "./", "macro_debugging": false, "vars": {}, "warn_error_options": {"error": [], "warn": [], "silence": []}, "which": "generate", "print": true, "populate_cache": true, "partial_parse_file_diff": true, "state_modified_compare_vars": false, "empty_catalog": false, "log_format_file": "debug", "version_check": true, "require_ref_searches_node_package_before_root": false, "log_format": "default", "partial_parse": true, "compile": true, "project_dir": "/home/runner/work/dwh-sm2/dwh-sm2", "require_batched_execution_for_custom_microbatch_strategy": false, "strict_mode": false, "introspect": true, "use_colors": true, "write_json": true, "favor_state": false, "source_freshness_run_project_hooks": true, "invocation_command": "dbt docs generate", "cache_selected_only": false, "require_explicit_package_overrides_for_builtin_materializations": true, "printer_width": 80, "require_nested_cumulative_type_params": false, "require_resource_names_without_spaces": true, "exclude": [], "defer": false, "state_modified_compare_more_unrendered_values": false, "quiet": false, "upload_to_artifacts_ingest_api": false, "send_anonymous_usage_stats": true, "use_fast_test_edges": false, "show_resource_report": false, "static_parser": true, "select": [], "log_file_max_bytes": 10485760, "require_yaml_configuration_for_mf_time_spines": false, "require_unique_project_resource_names": false, "validate_macro_args": false, "log_level_file": "debug", "require_generic_test_arguments_property": true, "skip_nodes_if_on_run_start_fails": false, "static": false, "log_path": "/home/runner/work/dwh-sm2/dwh-sm2/logs"}}