{"metadata": {"dbt_schema_version": "https://schemas.getdbt.com/dbt/run-results/v6.json", "dbt_version": "1.11.11", "generated_at": "2026-06-15T02:50:38.028166Z", "invocation_id": "3b1d4e88-0369-4b44-b0ef-d649c8cbe8cc", "invocation_started_at": "2026-06-15T02:50:37.216675Z", "env": {}}, "results": [{"status": "success", "timing": [{"name": "compile", "started_at": "2026-06-15T02:50:37.948750Z", "completed_at": "2026-06-15T02:50:37.956510Z"}, {"name": "execute", "started_at": "2026-06-15T02:50:37.960116Z", "completed_at": "2026-06-15T02:50:37.960138Z"}], "thread_id": "Thread-1 (worker)", "execution_time": 0.015883684158325195, "adapter_response": {}, "message": null, "failures": null, "unique_id": "seed.dwh_sm2.location_map", "compiled": null, "compiled_code": null, "relation_name": null, "batch_results": null}, {"status": "success", "timing": [{"name": "compile", "started_at": "2026-06-15T02:50:37.957596Z", "completed_at": "2026-06-15T02:50:37.959125Z"}, {"name": "execute", "started_at": "2026-06-15T02:50:37.963101Z", "completed_at": "2026-06-15T02:50:37.963114Z"}], "thread_id": "Thread-2 (worker)", "execution_time": 0.017726659774780273, "adapter_response": {}, "message": null, "failures": null, "unique_id": "seed.dwh_sm2.mapping", "compiled": null, "compiled_code": null, "relation_name": null, "batch_results": null}, {"status": "success", "timing": [{"name": "compile", "started_at": "2026-06-15T02:50:37.961024Z", "completed_at": "2026-06-15T02:50:37.962569Z"}, {"name": "execute", "started_at": "2026-06-15T02:50:37.966048Z", "completed_at": "2026-06-15T02:50:37.966059Z"}], "thread_id": "Thread-3 (worker)", "execution_time": 0.019092798233032227, "adapter_response": {}, "message": null, "failures": null, "unique_id": "seed.dwh_sm2.mapping_indoor", "compiled": null, "compiled_code": null, "relation_name": null, "batch_results": null}, {"status": "success", "timing": [{"name": "compile", "started_at": "2026-06-15T02:50:37.963913Z", "completed_at": "2026-06-15T02:50:37.965438Z"}, {"name": "execute", "started_at": "2026-06-15T02:50:37.966990Z", "completed_at": "2026-06-15T02:50:37.967001Z"}], "thread_id": "Thread-4 (worker)", "execution_time": 0.019005775451660156, "adapter_response": {}, "message": null, "failures": null, "unique_id": "seed.dwh_sm2.mapping_sources", "compiled": null, "compiled_code": null, "relation_name": null, "batch_results": null}, {"status": "success", "timing": [{"name": "compile", "started_at": "2026-06-15T02:50:37.969767Z", "completed_at": "2026-06-15T02:50:37.985851Z"}, {"name": "execute", "started_at": "2026-06-15T02:50:37.986371Z", "completed_at": "2026-06-15T02:50:37.986381Z"}], "thread_id": "Thread-6 (worker)", "execution_time": 0.017716407775878906, "adapter_response": {}, "message": null, "failures": null, "unique_id": "model.dwh_sm2.fact", "compiled": true, "compiled_code": "with source as ( --noqa\n    select cast(columns(*) as varchar) from read_csv('./gdrive/merged.csv')\n),\n\nunpivoted as (\n    unpivot source --noqa\n    on columns(* exclude (date))\n    into\n    name data_key_original\n    value data_value\n),\n\nmapped as (\n    select\n        unpivoted.date as \"time\", --noqa\n        mapping.location,\n        mapping.data_key,\n        unpivoted.data_value\n    from unpivoted\n    inner join \"dwh_sm2\".\"main\".\"mapping\" as mapping --noqa\n        on unpivoted.data_key_original = mapping.data_key_original\n    where unpivoted.date is not null\n),\n\nparams as (\n    select\n        date_trunc( --noqa\n            'month', now()) - interval (b.history - 1 --noqa\n            ) month as start_ts --noqa\n    from \"dwh_sm2\".\"main\".\"mapping_sources\" as b\n    where b.file_nm = 'fact.csv'\n),\n\nfinal as (\n    select\n        cast(time as timestamp) as time, --noqa\n        location,\n        data_key,\n        data_value\n    from mapped\n    union distinct\n    select * from read_csv('./gdrive/fact.csv')\n)\n\nselect *\nfrom final\nwhere time >= (select max(start_ts) from params) --noqa", "relation_name": "\"dwh_sm2\".\"main\".\"fact\"", "batch_results": null}, {"status": "success", "timing": [{"name": "compile", "started_at": "2026-06-15T02:50:37.981678Z", "completed_at": "2026-06-15T02:50:37.987414Z"}, {"name": "execute", "started_at": "2026-06-15T02:50:37.987909Z", "completed_at": "2026-06-15T02:50:37.987919Z"}], "thread_id": "Thread-8 (worker)", "execution_time": 0.01199197769165039, "adapter_response": {}, "message": null, "failures": null, "unique_id": "model.dwh_sm2.fact_indoor_temperature", "compiled": true, "compiled_code": "with source as (\n    select * from read_csv('./gdrive/all_sensors_merged.csv')\n),\n\nmapped as (\n    select\n        source.Datetime as \"time\", --noqa\n        mapping.location,\n        'temp_indoor' as data_key,\n        source.temperature_celsius as data_value\n    from source\n    inner join \"dwh_sm2\".\"main\".\"mapping_indoor\" as mapping --noqa\n        on source.location = mapping.sensor\n    where source.datetime is not null\n),\n\nparams as (\n    select\n        date_trunc( --noqa\n            'month', now()) - interval (b.history - 1 --noqa\n            ) month as start_ts --noqa\n    from \"dwh_sm2\".\"main\".\"mapping_sources\" as b\n    where b.file_nm = 'fact_indoor_temperature.csv'\n),\n\nfinal as (\n    select\n        time,\n        location,\n        data_key,\n        data_value\n    from mapped\n    union distinct\n    select *\n    from read_csv('./gdrive/fact_indoor_temperature.csv')\n)\n\nselect *\nfrom final\nwhere time >= (select max(start_ts) from params) --noqa", "relation_name": "\"dwh_sm2\".\"main\".\"fact_indoor_temperature\"", "batch_results": null}, {"status": "success", "timing": [{"name": "compile", "started_at": "2026-06-15T02:50:37.977616Z", "completed_at": "2026-06-15T02:50:37.995319Z"}, {"name": "execute", "started_at": "2026-06-15T02:50:37.995941Z", "completed_at": "2026-06-15T02:50:37.995952Z"}], "thread_id": "Thread-7 (worker)", "execution_time": 0.020707130432128906, "adapter_response": {}, "message": null, "failures": null, "unique_id": "model.dwh_sm2.fact_indoor_humidity", "compiled": true, "compiled_code": "with source as (\n    select * from read_csv('./gdrive/all_sensors_merged.csv')\n),\n\nmapped as (\n    select\n        source.Datetime as \"time\", --noqa\n        mapping.location,\n        'humidity_indoor' as data_key,\n        source.\"Relative_Humidity(%)\" as data_value --noqa\n    from source\n    inner join \"dwh_sm2\".\"main\".\"mapping_indoor\" as mapping --noqa\n        on source.location = mapping.sensor\n    where source.datetime is not null\n),\n\nparams as (\n    select\n        date_trunc( --noqa\n            'month', now()) - interval (b.history - 1 --noqa\n            ) month as start_ts --noqa\n    from \"dwh_sm2\".\"main\".\"mapping_sources\" as b\n    where b.file_nm = 'fact_indoor_humidity.csv'\n),\n\nfinal as (\n    select\n        time,\n        location,\n        data_key,\n        data_value\n    from mapped\n    union distinct\n    select *\n    from read_csv('./gdrive/fact_indoor_humidity.csv')\n)\n\nselect *\nfrom final\nwhere time >= (select max(start_ts) from params) --noqa", "relation_name": "\"dwh_sm2\".\"main\".\"fact_indoor_humidity\"", "batch_results": null}, {"status": "success", "timing": [{"name": "compile", "started_at": "2026-06-15T02:50:37.990144Z", "completed_at": "2026-06-15T02:50:38.019337Z"}, {"name": "execute", "started_at": "2026-06-15T02:50:38.019843Z", "completed_at": "2026-06-15T02:50:38.019853Z"}], "thread_id": "Thread-8 (worker)", "execution_time": 0.030843734741210938, "adapter_response": {}, "message": null, "failures": null, "unique_id": "test.dwh_sm2.not_null_fact_time.2257553dfe", "compiled": true, "compiled_code": "\n    \n    \n\n\n\nselect time\nfrom \"dwh_sm2\".\"main\".\"fact\"\nwhere time is null\n\n\n", "relation_name": null, "batch_results": null}, {"status": "success", "timing": [{"name": "compile", "started_at": "2026-06-15T02:50:38.014251Z", "completed_at": "2026-06-15T02:50:38.020764Z"}, {"name": "execute", "started_at": "2026-06-15T02:50:38.021273Z", "completed_at": "2026-06-15T02:50:38.021283Z"}], "thread_id": "Thread-12 (worker)", "execution_time": 0.008174896240234375, "adapter_response": {}, "message": null, "failures": null, "unique_id": "test.dwh_sm2.not_null_fact_indoor_humidity_time.40897f2842", "compiled": true, "compiled_code": "\n    \n    \n\n\n\nselect time\nfrom \"dwh_sm2\".\"main\".\"fact_indoor_humidity\"\nwhere time is null\n\n\n", "relation_name": null, "batch_results": null}, {"status": "success", "timing": [{"name": "compile", "started_at": "2026-06-15T02:50:38.003518Z", "completed_at": "2026-06-15T02:50:38.021970Z"}, {"name": "execute", "started_at": "2026-06-15T02:50:38.022557Z", "completed_at": "2026-06-15T02:50:38.022565Z"}], "thread_id": "Thread-7 (worker)", "execution_time": 0.025504589080810547, "adapter_response": {}, "message": null, "failures": null, "unique_id": "test.dwh_sm2.not_null_fact_indoor_temperature_time.06175171ac", "compiled": true, "compiled_code": "\n    \n    \n\n\n\nselect time\nfrom \"dwh_sm2\".\"main\".\"fact_indoor_temperature\"\nwhere time is null\n\n\n", "relation_name": null, "batch_results": null}], "elapsed_time": 0.16074419021606445, "args": {"favor_state": false, "profiles_dir": "./", "introspect": true, "strict_mode": false, "log_format": "default", "select": [], "state_modified_compare_vars": false, "version_check": true, "static_parser": true, "show_all_deprecations": false, "validate_macro_args": false, "which": "generate", "require_all_warnings_handled_by_warn_error": false, "vars": {}, "invocation_command": "dbt docs generate", "partial_parse": true, "sqlparse": {"MAX_GROUPING_DEPTH": null, "MAX_GROUPING_TOKENS": null}, "warn_error_options": {"error": [], "warn": [], "silence": []}, "print": true, "cache_selected_only": false, "require_nested_cumulative_type_params": false, "state_modified_compare_more_unrendered_values": false, "quiet": false, "require_ref_searches_node_package_before_root": false, "exclude": [], "indirect_selection": "eager", "use_colors": true, "source_freshness_run_project_hooks": true, "use_colors_file": true, "defer": false, "send_anonymous_usage_stats": true, "partial_parse_file_diff": true, "populate_cache": true, "log_file_max_bytes": 10485760, "log_format_file": "debug", "write_json": true, "require_explicit_package_overrides_for_builtin_materializations": true, "require_batched_execution_for_custom_microbatch_strategy": false, "show_resource_report": false, "macro_debugging": false, "static": false, "use_fast_test_edges": false, "require_generic_test_arguments_property": true, "empty_catalog": false, "require_unique_project_resource_names": false, "require_yaml_configuration_for_mf_time_spines": false, "skip_nodes_if_on_run_start_fails": false, "log_path": "/home/runner/work/dwh-sm2/dwh-sm2/logs", "compile": true, "log_level_file": "debug", "project_dir": "/home/runner/work/dwh-sm2/dwh-sm2", "printer_width": 80, "log_level": "info", "upload_to_artifacts_ingest_api": false, "require_resource_names_without_spaces": true}}