{"metadata": {"dbt_schema_version": "https://schemas.getdbt.com/dbt/sources/v3.json", "dbt_version": "1.10.9", "generated_at": "2025-08-18T01:05:24.031593Z", "invocation_id": "26069a61-e8a2-452b-b658-2b84744f9802", "invocation_started_at": "2025-08-18T01:05:21.652873Z", "env": {}}, "results": [{"unique_id": "source.dwh_sm2.csv_google_indoor.merged_indoor", "max_loaded_at": "0001-01-01T00:00:00+00:00", "snapshotted_at": "2025-08-18T01:05:24.007000+00:00", "max_loaded_at_time_ago_in_s": 63891075924.007, "status": "warn", "criteria": {"warn_after": {"count": 365, "period": "day"}, "error_after": {"count": null, "period": null}, "filter": null}, "adapter_response": {"_message": "OK"}, "timing": [{"name": "compile", "started_at": "2025-08-18T01:05:23.986489Z", "completed_at": "2025-08-18T01:05:23.986495Z"}, {"name": "execute", "started_at": "2025-08-18T01:05:23.987427Z", "completed_at": "2025-08-18T01:05:24.019838Z"}], "thread_id": "Thread-2 (worker)", "execution_time": 0.035696983337402344}, {"unique_id": "source.dwh_sm2.csv_google.merged", "max_loaded_at": "0001-01-01T00:00:00+00:00", "snapshotted_at": "2025-08-18T01:05:24.007000+00:00", "max_loaded_at_time_ago_in_s": 63891075924.007, "status": "warn", "criteria": {"warn_after": {"count": 365, "period": "day"}, "error_after": {"count": null, "period": null}, "filter": null}, "adapter_response": {"_message": "OK"}, "timing": [{"name": "compile", "started_at": "2025-08-18T01:05:23.984839Z", "completed_at": "2025-08-18T01:05:23.984846Z"}, {"name": "execute", "started_at": "2025-08-18T01:05:23.985784Z", "completed_at": "2025-08-18T01:05:24.021636Z"}], "thread_id": "Thread-1 (worker)", "execution_time": 0.03876185417175293}], "elapsed_time": 0.13317465782165527}