{"metadata": {"dbt_schema_version": "https://schemas.getdbt.com/dbt/sources/v3.json", "dbt_version": "1.9.2", "generated_at": "2025-02-20T01:46:17.237567Z", "invocation_id": "01bea9b7-ce39-4cfb-9fe0-b4e969c1ed6c", "env": {}}, "results": [{"unique_id": "source.dwh_sm2.csv_google.merged", "max_loaded_at": "0001-01-01T00:00:00+00:00", "snapshotted_at": "2025-02-20T01:46:17.221000+00:00", "max_loaded_at_time_ago_in_s": 63875612777.221, "status": "warn", "criteria": {"warn_after": {"count": 365, "period": "day"}, "error_after": {"count": null, "period": null}, "filter": null}, "adapter_response": {"_message": "OK"}, "timing": [{"name": "compile", "started_at": "2025-02-20T01:46:17.209031Z", "completed_at": "2025-02-20T01:46:17.209036Z"}, {"name": "execute", "started_at": "2025-02-20T01:46:17.209441Z", "completed_at": "2025-02-20T01:46:17.228628Z"}], "thread_id": "Thread-1 (worker)", "execution_time": 0.02068161964416504}], "elapsed_time": 0.17117524147033691}