{"metadata": {"dbt_schema_version": "https://schemas.getdbt.com/dbt/sources/v3.json", "dbt_version": "1.9.4", "generated_at": "2025-04-06T01:59:48.754375Z", "invocation_id": "8461915d-f0b7-446c-8d1e-3d9bc17d0ada", "env": {}}, "results": [{"unique_id": "source.dwh_sm2.csv_google.merged", "max_loaded_at": "0001-01-01T00:00:00+00:00", "snapshotted_at": "2025-04-06T01:59:48.739000+00:00", "max_loaded_at_time_ago_in_s": 63879501588.739, "status": "warn", "criteria": {"warn_after": {"count": 365, "period": "day"}, "error_after": {"count": null, "period": null}, "filter": null}, "adapter_response": {"_message": "OK"}, "timing": [{"name": "compile", "started_at": "2025-04-06T01:59:48.727444Z", "completed_at": "2025-04-06T01:59:48.727448Z"}, {"name": "execute", "started_at": "2025-04-06T01:59:48.727882Z", "completed_at": "2025-04-06T01:59:48.745861Z"}], "thread_id": "Thread-1 (worker)", "execution_time": 0.019353389739990234}], "elapsed_time": 0.09583497047424316}