{"metadata": {"dbt_schema_version": "https://schemas.getdbt.com/dbt/sources/v3.json", "dbt_version": "1.10.4", "generated_at": "2025-07-12T02:12:16.616677Z", "invocation_id": "be6e567f-3bbe-4469-8462-79c023a6049b", "invocation_started_at": "2025-07-12T02:12:14.385735Z", "env": {}}, "results": [{"unique_id": "source.dwh_sm2.csv_google_indoor.merged_indoor", "max_loaded_at": "0001-01-01T00:00:00+00:00", "snapshotted_at": "2025-07-12T02:12:16.595000+00:00", "max_loaded_at_time_ago_in_s": 63887883136.595, "status": "warn", "criteria": {"warn_after": {"count": 365, "period": "day"}, "error_after": {"count": null, "period": null}, "filter": null}, "adapter_response": {"_message": "OK"}, "timing": [{"name": "compile", "started_at": "2025-07-12T02:12:16.574820Z", "completed_at": "2025-07-12T02:12:16.574825Z"}, {"name": "execute", "started_at": "2025-07-12T02:12:16.575939Z", "completed_at": "2025-07-12T02:12:16.605708Z"}], "thread_id": "Thread-2 (worker)", "execution_time": 0.032994747161865234}, {"unique_id": "source.dwh_sm2.csv_google.merged", "max_loaded_at": "0001-01-01T00:00:00+00:00", "snapshotted_at": "2025-07-12T02:12:16.594000+00:00", "max_loaded_at_time_ago_in_s": 63887883136.594, "status": "warn", "criteria": {"warn_after": {"count": 365, "period": "day"}, "error_after": {"count": null, "period": null}, "filter": null}, "adapter_response": {"_message": "OK"}, "timing": [{"name": "compile", "started_at": "2025-07-12T02:12:16.574341Z", "completed_at": "2025-07-12T02:12:16.574361Z"}, {"name": "execute", "started_at": "2025-07-12T02:12:16.575265Z", "completed_at": "2025-07-12T02:12:16.607334Z"}], "thread_id": "Thread-1 (worker)", "execution_time": 0.035215139389038086}], "elapsed_time": 0.1217813491821289}