{"metadata": {"dbt_schema_version": "https://schemas.getdbt.com/dbt/sources/v3.json", "dbt_version": "1.11.2", "generated_at": "2026-01-06T01:04:13.082862Z", "invocation_id": "2df894e2-52be-4696-a6df-f3ad4c8f493b", "invocation_started_at": "2026-01-06T01:04:10.552044Z", "env": {}}, "results": [{"unique_id": "source.dwh_sm2.csv_google_indoor.merged_indoor", "max_loaded_at": "0001-01-01T00:00:00+00:00", "snapshotted_at": "2026-01-06T01:04:12.965882+00:00", "max_loaded_at_time_ago_in_s": 63903258252.96588, "status": "warn", "criteria": {"warn_after": {"count": 365, "period": "day"}, "error_after": {"count": null, "period": null}, "filter": null}, "adapter_response": {"_message": "OK"}, "timing": [{"name": "compile", "started_at": "2026-01-06T01:04:12.944687Z", "completed_at": "2026-01-06T01:04:12.944692Z"}, {"name": "execute", "started_at": "2026-01-06T01:04:12.945816Z", "completed_at": "2026-01-06T01:04:12.972439Z"}], "thread_id": "Thread-2 (worker)", "execution_time": 0.02984929084777832}, {"unique_id": "source.dwh_sm2.csv_google.merged", "max_loaded_at": "2025-12-31T17:00:40+00:00", "snapshotted_at": "2026-01-06T01:04:12.962435+00:00", "max_loaded_at_time_ago_in_s": 461012.962435, "status": "pass", "criteria": {"warn_after": {"count": 365, "period": "day"}, "error_after": {"count": null, "period": null}, "filter": null}, "adapter_response": {"_message": "OK"}, "timing": [{"name": "compile", "started_at": "2026-01-06T01:04:12.944225Z", "completed_at": "2026-01-06T01:04:12.944232Z"}, {"name": "execute", "started_at": "2026-01-06T01:04:12.945157Z", "completed_at": "2026-01-06T01:04:13.072809Z"}], "thread_id": "Thread-1 (worker)", "execution_time": 0.13072657585144043}], "elapsed_time": 0.21993589401245117}