{"metadata": {"dbt_schema_version": "https://schemas.getdbt.com/dbt/sources/v3.json", "dbt_version": "1.11.2", "generated_at": "2025-12-25T01:02:22.832944Z", "invocation_id": "cb085cca-1e05-4c7c-87ca-64da2637d170", "invocation_started_at": "2025-12-25T01:02:20.328115Z", "env": {}}, "results": [{"unique_id": "source.dwh_sm2.csv_google_indoor.merged_indoor", "max_loaded_at": "0001-01-01T00:00:00+00:00", "snapshotted_at": "2025-12-25T01:02:22.809187+00:00", "max_loaded_at_time_ago_in_s": 63902221342.80919, "status": "warn", "criteria": {"warn_after": {"count": 365, "period": "day"}, "error_after": {"count": null, "period": null}, "filter": null}, "adapter_response": {"_message": "OK"}, "timing": [{"name": "compile", "started_at": "2025-12-25T01:02:22.786180Z", "completed_at": "2025-12-25T01:02:22.786185Z"}, {"name": "execute", "started_at": "2025-12-25T01:02:22.787451Z", "completed_at": "2025-12-25T01:02:22.820901Z"}], "thread_id": "Thread-2 (worker)", "execution_time": 0.03686714172363281}, {"unique_id": "source.dwh_sm2.csv_google.merged", "max_loaded_at": "0001-01-01T00:00:00+00:00", "snapshotted_at": "2025-12-25T01:02:22.809259+00:00", "max_loaded_at_time_ago_in_s": 63902221342.80926, "status": "warn", "criteria": {"warn_after": {"count": 365, "period": "day"}, "error_after": {"count": null, "period": null}, "filter": null}, "adapter_response": {"_message": "OK"}, "timing": [{"name": "compile", "started_at": "2025-12-25T01:02:22.785693Z", "completed_at": "2025-12-25T01:02:22.785700Z"}, {"name": "execute", "started_at": "2025-12-25T01:02:22.786704Z", "completed_at": "2025-12-25T01:02:22.821839Z"}], "thread_id": "Thread-1 (worker)", "execution_time": 0.038393497467041016}], "elapsed_time": 0.13375139236450195}