{"metadata": {"dbt_schema_version": "https://schemas.getdbt.com/dbt/sources/v3.json", "dbt_version": "1.11.11", "generated_at": "2026-06-10T02:35:56.178356Z", "invocation_id": "d921319b-1b57-4fa1-852c-16d87efe16c3", "invocation_started_at": "2026-06-10T02:35:53.611926Z", "env": {}}, "results": [{"unique_id": "source.dwh_sm2.csv_google.merged", "max_loaded_at": "0001-01-01T00:00:00+00:00", "snapshotted_at": "2026-06-10T02:35:56.089985+00:00", "max_loaded_at_time_ago_in_s": 63916655756.08999, "status": "warn", "criteria": {"warn_after": {"count": 365, "period": "day"}, "error_after": {"count": null, "period": null}, "filter": null}, "adapter_response": {"_message": "OK"}, "timing": [{"name": "compile", "started_at": "2026-06-10T02:35:56.065926Z", "completed_at": "2026-06-10T02:35:56.065936Z"}, {"name": "execute", "started_at": "2026-06-10T02:35:56.066929Z", "completed_at": "2026-06-10T02:35:56.102540Z"}], "thread_id": "Thread-1 (worker)", "execution_time": 0.03898334503173828}, {"unique_id": "source.dwh_sm2.csv_google_indoor.merged_indoor", "max_loaded_at": "2026-06-08T10:35:00+00:00", "snapshotted_at": "2026-06-10T02:35:56.090075+00:00", "max_loaded_at_time_ago_in_s": 144056.090075, "status": "pass", "criteria": {"warn_after": {"count": 365, "period": "day"}, "error_after": {"count": null, "period": null}, "filter": null}, "adapter_response": {"_message": "OK"}, "timing": [{"name": "compile", "started_at": "2026-06-10T02:35:56.066428Z", "completed_at": "2026-06-10T02:35:56.066435Z"}, {"name": "execute", "started_at": "2026-06-10T02:35:56.067642Z", "completed_at": "2026-06-10T02:35:56.167729Z"}], "thread_id": "Thread-2 (worker)", "execution_time": 0.10351443290710449}], "elapsed_time": 0.18734979629516602}