{"metadata": {"dbt_schema_version": "https://schemas.getdbt.com/dbt/sources/v3.json", "dbt_version": "1.11.11", "generated_at": "2026-06-24T02:28:25.467923Z", "invocation_id": "5caf66f1-f47a-4dba-b95b-b2d284f725d9", "invocation_started_at": "2026-06-24T02:28:23.036272Z", "env": {}}, "results": [{"unique_id": "source.dwh_sm2.csv_google.merged", "max_loaded_at": "0001-01-01T00:00:00+00:00", "snapshotted_at": "2026-06-24T02:28:25.445816+00:00", "max_loaded_at_time_ago_in_s": 63917864905.445816, "status": "warn", "criteria": {"warn_after": {"count": 365, "period": "day"}, "error_after": {"count": null, "period": null}, "filter": null}, "adapter_response": {"_message": "OK"}, "timing": [{"name": "compile", "started_at": "2026-06-24T02:28:25.427452Z", "completed_at": "2026-06-24T02:28:25.427458Z"}, {"name": "execute", "started_at": "2026-06-24T02:28:25.428402Z", "completed_at": "2026-06-24T02:28:25.455105Z"}], "thread_id": "Thread-1 (worker)", "execution_time": 0.029844284057617188}, {"unique_id": "source.dwh_sm2.csv_google_indoor.merged_indoor", "max_loaded_at": "0001-01-01T00:00:00+00:00", "snapshotted_at": "2026-06-24T02:28:25.448836+00:00", "max_loaded_at_time_ago_in_s": 63917864905.44884, "status": "warn", "criteria": {"warn_after": {"count": 365, "period": "day"}, "error_after": {"count": null, "period": null}, "filter": null}, "adapter_response": {"_message": "OK"}, "timing": [{"name": "compile", "started_at": "2026-06-24T02:28:25.427949Z", "completed_at": "2026-06-24T02:28:25.427954Z"}, {"name": "execute", "started_at": "2026-06-24T02:28:25.429080Z", "completed_at": "2026-06-24T02:28:25.458091Z"}], "thread_id": "Thread-2 (worker)", "execution_time": 0.03226280212402344}], "elapsed_time": 0.11551594734191895}