{"metadata": {"dbt_schema_version": "https://schemas.getdbt.com/dbt/sources/v3.json", "dbt_version": "1.10.15", "generated_at": "2025-12-15T01:04:49.176659Z", "invocation_id": "1cb0e7f4-c8f7-44b7-adcc-4549bd3b3d49", "invocation_started_at": "2025-12-15T01:04:47.099120Z", "env": {}}, "results": [{"unique_id": "source.dwh_sm2.csv_google.merged", "max_loaded_at": "0001-01-01T00:00:00+00:00", "snapshotted_at": "2025-12-15T01:04:49.154905+00:00", "max_loaded_at_time_ago_in_s": 63901357489.15491, "status": "warn", "criteria": {"warn_after": {"count": 365, "period": "day"}, "error_after": {"count": null, "period": null}, "filter": null}, "adapter_response": {"_message": "OK"}, "timing": [{"name": "compile", "started_at": "2025-12-15T01:04:49.134342Z", "completed_at": "2025-12-15T01:04:49.134348Z"}, {"name": "execute", "started_at": "2025-12-15T01:04:49.135207Z", "completed_at": "2025-12-15T01:04:49.166203Z"}], "thread_id": "Thread-1 (worker)", "execution_time": 0.034010887145996094}, {"unique_id": "source.dwh_sm2.csv_google_indoor.merged_indoor", "max_loaded_at": "0001-01-01T00:00:00+00:00", "snapshotted_at": "2025-12-15T01:04:49.155008+00:00", "max_loaded_at_time_ago_in_s": 63901357489.15501, "status": "warn", "criteria": {"warn_after": {"count": 365, "period": "day"}, "error_after": {"count": null, "period": null}, "filter": null}, "adapter_response": {"_message": "OK"}, "timing": [{"name": "compile", "started_at": "2025-12-15T01:04:49.134795Z", "completed_at": "2025-12-15T01:04:49.134809Z"}, {"name": "execute", "started_at": "2025-12-15T01:04:49.135859Z", "completed_at": "2025-12-15T01:04:49.167086Z"}], "thread_id": "Thread-2 (worker)", "execution_time": 0.03427767753601074}], "elapsed_time": 0.11594343185424805}