{"metadata": {"dbt_schema_version": "https://schemas.getdbt.com/dbt/sources/v3.json", "dbt_version": "1.10.13", "generated_at": "2025-11-01T01:01:06.829706Z", "invocation_id": "98767c39-953a-4432-a060-a02a5fdb6fbb", "invocation_started_at": "2025-11-01T01:01:04.471594Z", "env": {}}, "results": [{"unique_id": "source.dwh_sm2.csv_google.merged", "max_loaded_at": "0001-01-01T00:00:00+00:00", "snapshotted_at": "2025-11-01T01:01:06.731024+00:00", "max_loaded_at_time_ago_in_s": 63897555666.731026, "status": "warn", "criteria": {"warn_after": {"count": 365, "period": "day"}, "error_after": {"count": null, "period": null}, "filter": null}, "adapter_response": {"_message": "OK"}, "timing": [{"name": "compile", "started_at": "2025-11-01T01:01:06.713251Z", "completed_at": "2025-11-01T01:01:06.713257Z"}, {"name": "execute", "started_at": "2025-11-01T01:01:06.714164Z", "completed_at": "2025-11-01T01:01:06.744697Z"}], "thread_id": "Thread-1 (worker)", "execution_time": 0.03362441062927246}, {"unique_id": "source.dwh_sm2.csv_google_indoor.merged_indoor", "max_loaded_at": "2025-10-31T09:26:00+00:00", "snapshotted_at": "2025-11-01T01:01:06.736533+00:00", "max_loaded_at_time_ago_in_s": 56106.736533, "status": "pass", "criteria": {"warn_after": {"count": 365, "period": "day"}, "error_after": {"count": null, "period": null}, "filter": null}, "adapter_response": {"_message": "OK"}, "timing": [{"name": "compile", "started_at": "2025-11-01T01:01:06.713700Z", "completed_at": "2025-11-01T01:01:06.713705Z"}, {"name": "execute", "started_at": "2025-11-01T01:01:06.714815Z", "completed_at": "2025-11-01T01:01:06.820110Z"}], "thread_id": "Thread-2 (worker)", "execution_time": 0.10850739479064941}], "elapsed_time": 0.19603562355041504}